commandpalette-0.4.1.data/data/share/man/man1/palette.1
commandpalette-0.4.1.data/scripts/palette
commandpalette-0.4.1.data/scripts/palette-rofi-script
commandpalette-0.4.1.data/scripts/paletted
libpalette/__init__.py
libpalette/command.py
libpalette/commands_manager.py
libpalette/configuration.py
libpalette/connection.py
libpalette/connection_handler.py
libpalette/exceptions.py
libpalette/keybindings_manager.py
libpalette/keybindings_manager_mock.py
libpalette/logger.py
libpalette/rofi.py
libpalette/server.py
libpalette/sxhkd.py
libpalette/sxhkd_process.py
libpalette/utils.py
libpalette/version.py
libpalette/scripts/__init__.py
libpalette/scripts/main.py
commandpalette-0.4.1.dist-info/LICENSE
commandpalette-0.4.1.dist-info/METADATA
commandpalette-0.4.1.dist-info/WHEEL
commandpalette-0.4.1.dist-info/top_level.txt
commandpalette-0.4.1.dist-info/RECORD
