Metadata-Version: 2.1
Name: commandpalette
Version: 0.4.1
Summary: A command palette for your operating system
Home-page: https://github.com/QazmoQwerty/palette
Author: Shalev Don Meiri
Author-email: sdonmeiri@gmail.com
License: MIT
Project-URL: Bug Tracker, https://github.com/QazmoQwerty/palette/issues
Platform: UNKNOWN
Classifier: Programming Language :: Python :: 3
Classifier: License :: OSI Approved :: MIT License
Classifier: Operating System :: POSIX :: Linux
Requires-Python: >=3.7
License-File: LICENSE
